athina_logger/__init__.py
athina_logger/api_key.py
athina_logger/athina_meta.py
athina_logger/constants.py
athina_logger/exception/custom_exception.py
athina_logger/feedback/__init__.py
athina_logger/feedback/user_feedback.py
athina_logger/inference_logger.py
athina_logger/langchain_handler.py
athina_logger/log_stream_inference/__init__.py
athina_logger/log_stream_inference/log_stream_inference.py
athina_logger/log_stream_inference/openai_chat_completion_stream.py
athina_logger/log_stream_inference/openai_completion_stream.py
athina_logger/openai_wrapper.py
athina_logger/request_helper.py
athina_logger/tracing/__init__.py
athina_logger/tracing/callback/__init__.py
athina_logger/tracing/callback/langchain.py
athina_logger/tracing/decorators/__init__.py
athina_logger/tracing/decorators/athina_decorator.py
athina_logger/tracing/models.py
athina_logger/tracing/span.py
athina_logger/tracing/trace.py
athina_logger/tracing/util.py
athina_logger/util/__init__.py
athina_logger/util/extract_model.py
athina_logger/util/token_count_helper.py
athina_logger-1.3.0.dist-info/LICENSE
athina_logger-1.3.0.dist-info/METADATA
athina_logger-1.3.0.dist-info/WHEEL
athina_logger-1.3.0.dist-info/RECORD
