Metadata-Version: 2.3
Name: athina-logger
Version: 1.3.0
Summary: 
License: MIT
Author: Shiv Sakhuja
Author-email: shiv@athina.ai
Requires-Python: >=3.9,<4.0
Classifier: License :: OSI Approved :: MIT License
Classifier: Programming Language :: Python :: 3
Classifier: Programming Language :: Python :: 3.9
Classifier: Programming Language :: Python :: 3.10
Classifier: Programming Language :: Python :: 3.11
Classifier: Programming Language :: Python :: 3.12
Classifier: Programming Language :: Python :: 3.13
Requires-Dist: langchain (>=0.0.350)
Requires-Dist: openai
Requires-Dist: pydantic (>=2.4.0,<3.0.0)
Requires-Dist: retrying (>=1.3.4,<2.0.0)
Requires-Dist: tiktoken (>=0.7.0,<0.8.0)
